tencentcloud/__init__.py
tencentcloud/common/__init__.py
tencentcloud/common/abstract_client.py
tencentcloud/common/abstract_client_async.py
tencentcloud/common/abstract_model.py
tencentcloud/common/circuit_breaker.py
tencentcloud/common/common_client.py
tencentcloud/common/common_client_async.py
tencentcloud/common/credential.py
tencentcloud/common/retry.py
tencentcloud/common/retry_async.py
tencentcloud/common/sign.py
tencentcloud/common/exception/__init__.py
tencentcloud/common/exception/tencent_cloud_sdk_exception.py
tencentcloud/common/http/__init__.py
tencentcloud/common/http/pre_conn.py
tencentcloud/common/http/request.py
tencentcloud/common/http/request_async.py
tencentcloud/common/profile/__init__.py
tencentcloud/common/profile/client_profile.py
tencentcloud/common/profile/http_profile.py
tencentcloud_sdk_python_common-3.1.41.dist-info/METADATA
tencentcloud_sdk_python_common-3.1.41.dist-info/WHEEL
tencentcloud_sdk_python_common-3.1.41.dist-info/top_level.txt
tencentcloud_sdk_python_common-3.1.41.dist-info/RECORD
